cpapi/OpenMaya.py
cpapi/OpenMayaAnim.py
cpapi/OpenMayaFX.py
cpapi/OpenMayaMPx.py
cpapi/OpenMayaRender.py
cpapi/OpenMayaUI.py
cpapi/__ALL.py
cpapi/__OpenMayaAnim__.py
cpapi/__OpenMayaAnim_array__.py
cpapi/__OpenMayaAnim_it__.py
cpapi/__OpenMayaFX__.py
cpapi/__OpenMayaFX_array__.py
cpapi/__OpenMayaMPx__.py
cpapi/__OpenMayaRender__.py
cpapi/__OpenMayaUI__.py
cpapi/__OpenMayaUI_array__.py
cpapi/__OpenMaya__.py
cpapi/__OpenMaya_array__.py
cpapi/__OpenMaya_it__.py
cpapi/__init__.py
cpapi/all.py
cpapi/init_imp.py
cpapi/iter.py
cpapi/utils.py
cpapi/_api/OpenMaya.py
cpapi/_api/OpenMayaAnim.py
cpapi/_api/OpenMayaFX.py
cpapi/_api/OpenMayaMPx.py
cpapi/_api/OpenMayaRender.py
cpapi/_api/OpenMayaUI.py
cpapi/_api/__init__.py
cpapi/_api/_run_lib.py
cpapi-1.0.4.dist-info/LICENSE
cpapi-1.0.4.dist-info/METADATA
cpapi-1.0.4.dist-info/WHEEL
cpapi-1.0.4.dist-info/top_level.txt
cpapi-1.0.4.dist-info/RECORD
