Metadata-Version: 2.1
Name: cpapi
Version: 1.0.4
Summary: OpenMaya api 封装
Author-email: cpcgskill <cpcgskill@outlook.com>
License: Apache Software License (Apache 2.0)
Project-URL: Homepage, https://github.com/cpcgskill/cpapi
Project-URL: Bug Tracker, https://github.com/cpcgskill/cpapi/issues
Classifier: License :: OSI Approved :: Apache Software License
Classifier: Programming Language :: Python
Classifier: Programming Language :: Python :: 2
Classifier: Programming Language :: Python :: 2.7
Classifier: Programming Language :: Python :: 3
Classifier: Programming Language :: Python :: 3.6
Classifier: Programming Language :: Python :: 3.7
Classifier: Programming Language :: Python :: 3.8
Classifier: Programming Language :: Python :: 3.9
Classifier: Programming Language :: Python :: 3.10
Classifier: Programming Language :: Python :: Implementation :: CPython
Requires-Python: !=3.0.*,!=3.1.*,!=3.2.*,!=3.3.*,!=3.4.*,!=3.5.*,>=2.7
License-File: LICENSE
